beamingfactor/BeamingFactor.py
beamingfactor/WAVE_PHOENIX-ACES-AGSS-COND-2011.fits
beamingfactor/__init__.py
beamingfactor/PassBandFile/GAIA_GAIA3.G.dat.P
beamingfactor/PassBandFile/GAIA_GAIA3.Gbp.dat.P
beamingfactor/PassBandFile/GAIA_GAIA3.Grp.dat.P
beamingfactor/PassBandFile/Generic_Bessell.B.dat.E
beamingfactor/PassBandFile/Generic_Bessell.I.dat.E
beamingfactor/PassBandFile/Generic_Bessell.R.dat.E
beamingfactor/PassBandFile/Generic_Bessell.U.dat.E
beamingfactor/PassBandFile/Generic_Bessell.V.dat.E
beamingfactor/PassBandFile/Kepler_Kepler.K.dat.P
beamingfactor/PassBandFile/NUV_throughput.txt.P
beamingfactor/PassBandFile/SLOAN_SDSS.g.dat.P
beamingfactor/PassBandFile/SLOAN_SDSS.i.dat.P
beamingfactor/PassBandFile/SLOAN_SDSS.r.dat.P
beamingfactor/PassBandFile/SLOAN_SDSS.u.dat.P
beamingfactor/PassBandFile/SLOAN_SDSS.z.dat.P
beamingfactor/PassBandFile/TESS_TESS.Red.dat.E
beamingfactor/PassBandFile/g_throughput.txt.P
beamingfactor/PassBandFile/i_throughput.txt.P
beamingfactor/PassBandFile/r_throughput.txt.P
beamingfactor/PassBandFile/u_throughput.txt.P
beamingfactor/PassBandFile/y_throughput.txt.P
beamingfactor/PassBandFile/z_throughput.txt.P
beamingfactor-1.0.2.dist-info/LICENSE
beamingfactor-1.0.2.dist-info/METADATA
beamingfactor-1.0.2.dist-info/WHEEL
beamingfactor-1.0.2.dist-info/top_level.txt
beamingfactor-1.0.2.dist-info/RECORD
