Metadata-Version: 2.1
Name: beamingfactor
Version: 1.0.2
Summary: Program to compute beaming factor.
Home-page: https://github.com/shift-method/beamingfactor
Author: Chuanjie Zheng
Author-email: zhengchuanjie@nao.cas.cn
License: MIT
Classifier: License :: OSI Approved :: MIT License
Classifier: Programming Language :: Python
Classifier: Programming Language :: Python :: 3
Classifier: Programming Language :: Python :: 3.6
Classifier: Programming Language :: Python :: Implementation :: CPython
Classifier: Programming Language :: Python :: Implementation :: PyPy
Requires-Python: >=3.6.0
License-File: LICENSE
Requires-Dist: scipy
Requires-Dist: numpy
Requires-Dist: matplotlib
Requires-Dist: astropy
Requires-Dist: dust-extinction
